[
  {
    "prediction": " (D)",
    "gen_start_token": -1,
    "example_id": "121_4",
    "answers": "(D)"
  },
  {
    "prediction": " (A)",
    "gen_start_token": -1,
    "example_id": "66_3",
    "answers": "(B)"
  },
  {
    "prediction": " (B)",
    "gen_start_token": -1,
    "example_id": "39_5",
    "answers": "(B)"
  },
  {
    "prediction": " (A)",
    "gen_start_token": -1,
    "example_id": "60_4",
    "answers": "(D)"
  },
  {
    "prediction": " (B)",
    "gen_start_token": -1,
    "example_id": "110_5",
    "answers": "(B)"
  },
  {
    "prediction": " (A)",
    "gen_start_token": -1,
    "example_id": "6_4",
    "answers": "(D)"
  },
  {
    "prediction": " (C)",
    "gen_start_token": -1,
    "example_id": "109_4",
    "answers": "(C)"
  },
  {
    "prediction": " (C)",
    "gen_start_token": -1,
    "example_id": "102_4",
    "answers": "(C)"
  },
  {
    "prediction": " (B)",
    "gen_start_token": -1,
    "example_id": "61_5",
    "answers": "(B)"
  },
  {
    "prediction": " (D)",
    "gen_start_token": -1,
    "example_id": "46_4",
    "answers": "(B)"
  },
  {
    "prediction": " (D)",
    "gen_start_token": -1,
    "example_id": "97_5",
    "answers": "(C)"
  },
  {
    "prediction": " (C)",
    "gen_start_token": -1,
    "example_id": "107_5",
    "answers": "(C)"
  },
  {
    "prediction": " (B)",
    "gen_start_token": -1,
    "example_id": "92_3",
    "answers": "(B)"
  },
  {
    "prediction": " (D)",
    "gen_start_token": -1,
    "example_id": "46_5",
    "answers": "(C)"
  },
  {
    "prediction": " (B)",
    "gen_start_token": -1,
    "example_id": "28_4",
    "answers": "(A)"
  },
  {
    "prediction": " (C)",
    "gen_start_token": -1,
    "example_id": "57_3",
    "answers": "(B)"
  },
  {
    "prediction": " (A)",
    "gen_start_token": -1,
    "example_id": "79_4",
    "answers": "(C)"
  },
  {
    "prediction": " (D)",
    "gen_start_token": -1,
    "example_id": "15_5",
    "answers": "(E)"
  },
  {
    "prediction": " (A)",
    "gen_start_token": -1,
    "example_id": "109_3",
    "answers": "(C)"
  },
  {
    "prediction": " (D)",
    "gen_start_token": -1,
    "example_id": "120_4",
    "answers": "(D)"
  },
  {
    "prediction": " (B)",
    "gen_start_token": -1,
    "example_id": "9_5",
    "answers": "(C)"
  },
  {
    "prediction": " (D)",
    "gen_start_token": -1,
    "example_id": "93_4",
    "answers": "(B)"
  },
  {
    "prediction": " (A)",
    "gen_start_token": -1,
    "example_id": "4_3",
    "answers": "(C)"
  },
  {
    "prediction": " (C)",
    "gen_start_token": -1,
    "example_id": "78_4",
    "answers": "(C)"
  },
  {
    "prediction": " (C)",
    "gen_start_token": -1,
    "example_id": "51_4",
    "answers": "(A)"
  },
  {
    "prediction": " (C)",
    "gen_start_token": -1,
    "example_id": "104_5",
    "answers": "(C)"
  },
  {
    "prediction": " (C)",
    "gen_start_token": -1,
    "example_id": "72_3",
    "answers": "(B)"
  },
  {
    "prediction": " (C)",
    "gen_start_token": -1,
    "example_id": "18_4",
    "answers": "(D)"
  },
  {
    "prediction": " (C)",
    "gen_start_token": -1,
    "example_id": "68_4",
    "answers": "(C)"
  },
  {
    "prediction": " (C)",
    "gen_start_token": -1,
    "example_id": "37_5",
    "answers": "(C)"
  },
  {
    "prediction": " (D)",
    "gen_start_token": -1,
    "example_id": "21_4",
    "answers": "(D)"
  },
  {
    "prediction": " (D)",
    "gen_start_token": -1,
    "example_id": "80_4",
    "answers": "(D)"
  },
  {
    "prediction": " (B)",
    "gen_start_token": -1,
    "example_id": "83_4",
    "answers": "(B)"
  },
  {
    "prediction": " (E)",
    "gen_start_token": -1,
    "example_id": "112_5",
    "answers": "(B)"
  },
  {
    "prediction": " (A)",
    "gen_start_token": -1,
    "example_id": "101_5",
    "answers": "(A)"
  },
  {
    "prediction": " (C)",
    "gen_start_token": -1,
    "example_id": "94_5",
    "answers": "(A)"
  },
  {
    "prediction": " (B)",
    "gen_start_token": -1,
    "example_id": "94_3",
    "answers": "(B)"
  },
  {
    "prediction": " (C)",
    "gen_start_token": -1,
    "example_id": "100_5",
    "answers": "(C)"
  },
  {
    "prediction": " (B)",
    "gen_start_token": -1,
    "example_id": "39_4",
    "answers": "(A)"
  },
  {
    "prediction": " (E)",
    "gen_start_token": -1,
    "example_id": "95_5",
    "answers": "(C)"
  },
  {
    "prediction": " (C)",
    "gen_start_token": -1,
    "example_id": "26_3",
    "answers": "(A)"
  },
  {
    "prediction": " (C)",
    "gen_start_token": -1,
    "example_id": "51_3",
    "answers": "(A)"
  },
  {
    "prediction": " (B)",
    "gen_start_token": -1,
    "example_id": "16_3",
    "answers": "(B)"
  },
  {
    "prediction": " (C)",
    "gen_start_token": -1,
    "example_id": "15_3",
    "answers": "(A)"
  },
  {
    "prediction": " (A)",
    "gen_start_token": -1,
    "example_id": "68_5",
    "answers": "(E)"
  },
  {
    "prediction": " (B)",
    "gen_start_token": -1,
    "example_id": "44_4",
    "answers": "(C)"
  },
  {
    "prediction": " (A)",
    "gen_start_token": -1,
    "example_id": "47_3",
    "answers": "(A)"
  },
  {
    "prediction": " (A)",
    "gen_start_token": -1,
    "example_id": "9_4",
    "answers": "(B)"
  },
  {
    "prediction": " (D)",
    "gen_start_token": -1,
    "example_id": "48_4",
    "answers": "(D)"
  },
  {
    "prediction": " (A)",
    "gen_start_token": -1,
    "example_id": "90_4",
    "answers": "(A)"
  },
  {
    "prediction": " (D)",
    "gen_start_token": -1,
    "example_id": "7_4",
    "answers": "(D)"
  },
  {
    "prediction": " (C)",
    "gen_start_token": -1,
    "example_id": "13_4",
    "answers": "(C)"
  },
  {
    "prediction": " (D)",
    "gen_start_token": -1,
    "example_id": "15_4",
    "answers": "(D)"
  },
  {
    "prediction": " (A)",
    "gen_start_token": -1,
    "example_id": "17_5",
    "answers": "(E)"
  },
  {
    "prediction": " (B)",
    "gen_start_token": -1,
    "example_id": "83_3",
    "answers": "(B)"
  },
  {
    "prediction": " (A)",
    "gen_start_token": -1,
    "example_id": "118_4",
    "answers": "(A)"
  },
  {
    "prediction": " (B)",
    "gen_start_token": -1,
    "example_id": "3_3",
    "answers": "(A)"
  },
  {
    "prediction": " (B)",
    "gen_start_token": -1,
    "example_id": "115_3",
    "answers": "(B)"
  },
  {
    "prediction": " (A)",
    "gen_start_token": -1,
    "example_id": "94_4",
    "answers": "(A)"
  },
  {
    "prediction": " (D)",
    "gen_start_token": -1,
    "example_id": "35_5",
    "answers": "(D)"
  },
  {
    "prediction": " (D)",
    "gen_start_token": -1,
    "example_id": "73_5",
    "answers": "(B)"
  },
  {
    "prediction": " (B)",
    "gen_start_token": -1,
    "example_id": "92_5",
    "answers": "(B)"
  },
  {
    "prediction": " (B)",
    "gen_start_token": -1,
    "example_id": "78_3",
    "answers": "(A)"
  },
  {
    "prediction": " (C)",
    "gen_start_token": -1,
    "example_id": "47_4",
    "answers": "(C)"
  },
  {
    "prediction": " (A)",
    "gen_start_token": -1,
    "example_id": "109_5",
    "answers": "(D)"
  },
  {
    "prediction": " (E)",
    "gen_start_token": -1,
    "example_id": "38_5",
    "answers": "(E)"
  },
  {
    "prediction": " (C)",
    "gen_start_token": -1,
    "example_id": "81_4",
    "answers": "(A)"
  },
  {
    "prediction": " (C)",
    "gen_start_token": -1,
    "example_id": "44_3",
    "answers": "(C)"
  },
  {
    "prediction": " (A)",
    "gen_start_token": -1,
    "example_id": "26_4",
    "answers": "(D)"
  },
  {
    "prediction": " (B)",
    "gen_start_token": -1,
    "example_id": "123_5",
    "answers": "(C)"
  },
  {
    "prediction": " (C)",
    "gen_start_token": -1,
    "example_id": "82_3",
    "answers": "(A)"
  },
  {
    "prediction": " (B)",
    "gen_start_token": -1,
    "example_id": "5_5",
    "answers": "(B)"
  },
  {
    "prediction": " (C)",
    "gen_start_token": -1,
    "example_id": "113_5",
    "answers": "(C)"
  },
  {
    "prediction": " (A)",
    "gen_start_token": -1,
    "example_id": "33_4",
    "answers": "(A)"
  },
  {
    "prediction": " (A)",
    "gen_start_token": -1,
    "example_id": "60_5",
    "answers": "(A)"
  },
  {
    "prediction": " (D)",
    "gen_start_token": -1,
    "example_id": "120_5",
    "answers": "(A)"
  },
  {
    "prediction": " (A)",
    "gen_start_token": -1,
    "example_id": "76_4",
    "answers": "(A)"
  },
  {
    "prediction": " (A)",
    "gen_start_token": -1,
    "example_id": "84_5",
    "answers": "(C)"
  },
  {
    "prediction": " (A)",
    "gen_start_token": -1,
    "example_id": "40_5",
    "answers": "(E)"
  },
  {
    "prediction": " (B)",
    "gen_start_token": -1,
    "example_id": "119_3",
    "answers": "(B)"
  },
  {
    "prediction": " (E)",
    "gen_start_token": -1,
    "example_id": "48_5",
    "answers": "(E)"
  },
  {
    "prediction": " (C)",
    "gen_start_token": -1,
    "example_id": "88_4",
    "answers": "(A)"
  },
  {
    "prediction": " (E)",
    "gen_start_token": -1,
    "example_id": "80_5",
    "answers": "(D)"
  },
  {
    "prediction": " (A)",
    "gen_start_token": -1,
    "example_id": "117_3",
    "answers": "(A)"
  },
  {
    "prediction": " (C)",
    "gen_start_token": -1,
    "example_id": "16_5",
    "answers": "(B)"
  },
  {
    "prediction": " (A)",
    "gen_start_token": -1,
    "example_id": "110_3",
    "answers": "(A)"
  },
  {
    "prediction": " (A)",
    "gen_start_token": -1,
    "example_id": "30_3",
    "answers": "(B)"
  },
  {
    "prediction": " (D)",
    "gen_start_token": -1,
    "example_id": "53_5",
    "answers": "(D)"
  },
  {
    "prediction": " (E)",
    "gen_start_token": -1,
    "example_id": "75_5",
    "answers": "(A)"
  },
  {
    "prediction": " (B)",
    "gen_start_token": -1,
    "example_id": "10_3",
    "answers": "(B)"
  },
  {
    "prediction": " (B)",
    "gen_start_token": -1,
    "example_id": "32_4",
    "answers": "(D)"
  },
  {
    "prediction": " (A)",
    "gen_start_token": -1,
    "example_id": "12_5",
    "answers": "(A)"
  },
  {
    "prediction": " (A)",
    "gen_start_token": -1,
    "example_id": "17_3",
    "answers": "(B)"
  }
]